[
    {


        
    "id": "fid1A",
    "url": "https://mutia1503.ukielaki88.workers.dev/0:/Indonesia%20jadul/permainan%20bulan%20desember%20(1990).mp4",
    "title": "Permainanan dibulan desember (1990)",
    "img": "https://posterfilm.pages.dev/poster/film_lawas/Bulan_desember.webp"
  },
  {
    "id": "fid2b",
    "url": "https://mutia1503.ukielaki88.workers.dev/0:/Indonesia%20jadul/hukum%20karma%20(1982).mp4",
    "title": "Hukum karma (1982)",
    "img": "https://posterfilm.pages.dev/poster/film_lawas/Hukum_karma.webp"
  },
  {
    "id": "fid3c",
    "url": "https://mutia1503.ukielaki88.workers.dev/0:/Indonesia%20jadul/dukun%20ilmu%20hitam%20(1981).mp4",
    "title": "Dukun ilmu hitam (1981)",
    "img": "https://posterfilm.pages.dev/poster/film_lawasDukun_ilmu_hitam.webp"
  },
  {
    "id": "fid4d",
    "url": "https://movieku.ukielaki8387.workers.dev/0:/Indo%20jadul/titian%20serambut%20dibelah%20tujuh%20(1959).mp4",
    "title": "Titian serambut dibelah tujuh (1959)",
    "img": "https://posterfilm.pages.dev/poster/film_lawas/Titian_serambut.webp"
  },
  {
    "id": "fid5e",
    "url": "https://movieku.ukielaki8387.workers.dev/0:/Indo%20jadul/tjoet%20nyak%20dhien%20(1988).mp4",
    "title": "Tjoet nyak dhien (1988)",
    "img": "https://posterfilm.pages.dev/poster/film_lawas/Tjoet_nyak_dhien.webp"
  },
  {
    "id": "fid6f",
    "url": "https://movieku.ukielaki8387.workers.dev/0:/Indo%20jadul/tak%20seindah%20kasih%20mama%20(1986).mp4",
    "title": "Tak seindah kasih mama (1986)",
    "img": "https://posterfilm.pages.dev/poster/film_lawas/Tak_seindah_kasih_mama.webp"
  },
  {
    "id": "fid7g",
    "url": "https://movieku.ukielaki8387.workers.dev/0:/Indo%20jadul/akibat%20buah%20terlarang%20(1984).mp4",
    "title": "Akibat buah terlarang (1984)",
    "img": "https://posterfilm.pages.dev/poster/film_lawas/Buah_terlarang.webp"
  },
  {
    "id": "fid8h",
    "url": "https://movieku.ukielaki8387.workers.dev/0:/Indo%20jadul/cubit-cubitan%20(1979).mp4",
    "title": "Cubit-cubitan (1979)",
    "img": "https://posterfilm.pages.dev/poster/film_lawas/Cubit.webp"
  },
  {
    "id": "fid9i",
    "url": "https://movieku.ukielaki8387.workers.dev/0:/Indo%20jadul/krikil-krikil%20tajam%20(1986).mp4",
    "title": "Kerikil-kerikil tajam (1986)",
    "img": "https://posterfilm.pages.dev/poster/film_lawas/Kerikil_tajam.webp"
  },
  {
    "id": "fid10j",
    "url": "https://movieku.ukielaki8387.workers.dev/0:/Indo%20jadul/macan%20kampus%20(1987).mp4",
    "title": "Macan kampus (1987)",
    "img": "https://posterfilm.pages.dev/poster/film_lawas/Macan_kampus.webp"
  },
  {
    "id": "fid11k",
    "url": "https://movieku.ukielaki8387.workers.dev/0:/Indo%20jadul/Gitar%20Tua%20Oma%20Irama%20(1976)%20Film%20Indonesia.mp4",
    "title": "Rhoma irama gitar tua (1976)",
    "img": "https://posterfilm.pages.dev/poster/film_lawas/Gitartua.webp"
  },
  {
    "id": "fid12l",
    "url": "https://movieku.ukielaki8387.workers.dev/0:/Indo%20jadul/Rhoma%20Irama%20Berkelana%20I%20(1978).mp4",
    "title": "Rhoma irama Berkelana part 1 (1978)",
    "img": "https://posterfilm.pages.dev/poster/film_lawas/Berkelana1.webp"
  },
  {
    "id": "fid13m",
    "url": "https://movieku.ukielaki8387.workers.dev/0:/Indo%20jadul/Rhoma%20Irama%20Berkelana%20II%20(1978).mp4",
    "title": "Rhoma irama berkelana part 2 (1978)",
    "img": "https://posterfilm.pages.dev/poster/film_lawas/Berkelana2.webp"
  },
  {
        "id": "fid1",
        "url": "https://mutia1503.ukielaki88.workers.dev/0:/Album%20film%202/Indonesia%20jadul/Pengabdi%20Setan%20(1980).mp4",
        "title": "Pengabdi Setan (1980)",
        "img": "https://cdn.jsdelivr.net/gh/Ukie4321/Mrzybposter@main/PicRetouch_20251209_191006338.webp"
    },
    {
        "id": "fid2",
        "url": "https://movieku.ukielaki8387.workers.dev/0:/Indo%20jadul/Bayi.Ajaib.1982.mp4",
        "title": "bayi ajaib 1982",
        "img": "https://i.pinimg.com/736x/62/83/e5/6283e508c875be8e07928bad5abcd96f.jpg"
    },
    {
        "id": "fid3",
        "url": "https://movieku.ukielaki8387.workers.dev/0:/Indo%20jadul/Barang%20Terlarang%20(1987).mp4",
        "title": "Barang terlarang (1987)",
        "img": "https://i.pinimg.com/736x/66/a5/3e/66a53edafa1ad78bab0d81dd3ed60742.jpg"
    },
    {
        "id": "fid4",
        "url": "https://mutia1503.ukielaki88.workers.dev/0:/Indonesia%20jadul/BUAYE%20GILE.%20Kualitas%20HD.%20Full%20Movie.webm",
        "title": "Benyamin buaye gile",
        "img": "https://i.pinimg.com/736x/24/c1/a2/24c1a23116391a15959d98d49bb16412.jpg"
    },
    {
        "id": "fid5",
        "url": "https://movieku.ukielaki8387.workers.dev/0:/Indo%20jadul/lukisan%20berlumur%20darah%201988.mp4",
        "title": "Lukisan berlumur darah (1988)",
        "img": "https://i.pinimg.com/736x/d9/0c/82/d90c82d319f004b59836f7647f274fa9.jpg"
    },
    {
        "id": "fid6",
        "url": "https://movieku.ukielaki8387.workers.dev/0:/Indo%20jadul/Gengsi.Dooong.1980.1080p.mp4",
        "title": "Warkop dki Gengsi dong (1980)",
        "img": "https://i.pinimg.com/736x/95/48/88/95488811395bfbf00edbdf41f3b4bf1b.jpg"
    },
    {
        "id": "fid7",
        "url": "https://movieku.ukielaki8387.workers.dev/0:/Indo%20jadul/djakarta%201966.mp4",
        "title": "Djakarta 1966 (1966)",
        "img": "https://i.pinimg.com/736x/a1/b9/e0/a1b9e09b95bfd84a2c078e252aad29df.jpg"
    },
    {
        "id": "fid8",
        "url": "https://movieku.ukielaki8387.workers.dev/0:/Indo%20jadul/operasi%20trisula%20(1987).mp4",
        "title": "operasi trisula (1987)",
        "img": "https://i.pinimg.com/736x/0b/85/0f/0b850ff53a193b440e6ca019e34c36f1.jpg"
    },
    {
        "id": "fid9",
        "url": "https://movieku.ukielaki8387.workers.dev/0:/Indo%20jadul/SI%20DOEL%20ANAK%20MODERN%20(1976)%20FULL%20MOVIE%20HD%20-%20BENYAMIN%20SUEB,%20CHRISTINE%20HAKIM,%20S.%20BONO_7760.mp4",
        "title": "Benyamin Si doel anak moderen (1976)",
        "img": "https://i.pinimg.com/736x/09/6e/cd/096ecd2effa8e04138cd121e912df41a.jpg"
    },
    {
        "id": "fid10",
        "url": "https://movieku.ukielaki8387.workers.dev/0:/Indo%20jadul/PINANGAN%20(1976)%20FULL%20MOVIE%20HD%20-%20BENYAMIN%20SUEB,%20RIMA%20MELATI,%20SUROTO_4335.mp4",
        "title": "Benyamin pinangan (1976)",
        "img": "https://i.pinimg.com/736x/81/51/29/815129e5db22763b58ae008937649355.jpg"
    },
    {
        "id": "fid11",
        "url": "https://movieku.ukielaki8387.workers.dev/0:/Indo%20jadul/SI%20BUTA%20DARI%20GOA%20HANTU%20(1970)%20FULL%20MOVIE%20HD%20-%20RATNO%20TIMOER,%20SRI%20REDJEKI,%20KUSNO%20SUDJARWADI.mp4",
        "title": "Si buta dari gua hantu(1970)",
        "img": "https://cdn.jsdelivr.net/gh/Ukie4321/Mrzybposter@main/PicRetouch_20251209_190939690.webp"
    },
    {
        "id": "fid12",
        "url": "https://movieku.ukielaki8387.workers.dev/0:/Indo%20jadul/ANAK%20EMAS%20(1976)%20FULL%20MOVIE%20HD%20-%20ADI%20BING%20SLAMET,%20YATNI%20ARDI,%20EDDY%20SUD,%20ALAM%20SURAWIJAYA.mp4",
        "title": "Anak emas(1976)",
        "img": "https://i.pinimg.com/736x/13/14/a9/1314a901bd4871f0e29f9996468cd4c1.jpg"
    },
    {
        "id": "fid13",
        "url": "https://mutia1503.ukielaki88.workers.dev/0:/Film%20jadul%20lagi/NIKMATNYA%20CINTA%20(1980)%20FULL%20MOVIE%20HD(720P_HD).mp4",
        "title": "Rano karno Nikmatnya cinta 1980",
        "img": "https://i.pinimg.com/736x/7e/e4/00/7ee400de8d49ed87933bf27f26348005.jpg"
    },
    {
        "id": "fid14",
        "url": "https://mutia1503.ukielaki88.workers.dev/0:/Film%20jadul%20lagi/PELANGI%20DI%20LANGIT%20SINGOSARI%20(KEN%20DEDES)%20(1972)%20FULL%20MOVIE%20HD%20-%20EMILIA%20CONTESSA_%20PONG%20HARJATMO(720P_HD).mp4",
        "title": "pelangi dilangit singosari 1972",
        "img": "https://i.pinimg.com/736x/7b/49/a9/7b49a99e8f8acea847a83b3c867f1fb1.jpg"
    },
    {
        "id": "fid15",
        "url": "https://mutia1503.ukielaki88.workers.dev/0:/Film%20jadul%20lagi/PENANGKAL%20ILMU%20TELUH%20(1979)%20FULL%20MOVIE%20HD%20-%20DEBBIE%20CYNTHIA%20DEWI_%20HENDRA%20CIPTA_%20MUNI%20CADER(720P_60FPS).mp4",
        "title": "penangkal ilmu teluh 1979",
        "img": "https://i.pinimg.com/736x/03/c7/61/03c76124ebd13502416b00c19c52b9d8.jpg"
    },
    {
        "id": "fid16",
        "url": "https://mutia1503.ukielaki88.workers.dev/0:/Film%20jadul%20lagi/PENDEKAR%20SUMUR%20TUDJUH%20(1971)%20FULL%20MOVIE%20HD%20-%20WAHAB%20ABDI_%20MILA%20KARMILA_%20AGUS%20RAMLAN(720P_60FPS).mp4",
        "title": "pendekar sumur tujuh 1971",
        "img": "https://i.pinimg.com/736x/3f/6f/af/3f6faffeec559f60d72c25bff073e9b8.jpg"
    },
    {
        "id": "fid17",
        "url": "https://mutia1503.ukielaki88.workers.dev/0:/Film%20jadul%20lagi/PERAWAN%20LEMBAH%20WILIS%20(1993)%20FULL%20MOVIE%20HD%20-%20BARRY%20PRIMA_%20AYU%20YOHANA_%20BARON%20HERMANTO(720P_HD).mp4",
        "title": "perawan lembah wilis 1993",
        "img": "https://i.pinimg.com/736x/ed/58/7a/ed587ad394841492190ccbe250cdcf63.jpg"
    },
    {
        "id": "fid18",
        "url": "https://mutia1503.ukielaki88.workers.dev/0:/Film%20jadul%20lagi/PRABU%20ANGLINGDARMA%20III%20(PEMBURU%20DI%20NERAKA)%20(1994)%20FULL%20MOVIE%20HD%20-%20BARRY%20PRIMA_%20FENDY%20PRADANA(720P_HD).mp4",
        "title": "Barry prima prabu anglingdarma 1994",
        "img": "https://i.pinimg.com/736x/33/34/f4/3334f4d5408998fa31b08d1e8aa12238.jpg"
    },
    {
        "id": "fid19",
        "url": "https://mutia1503.ukielaki88.workers.dev/0:/Film%20jadul%20lagi/SI%20KABAYAN%20DAN%20ANAK%20JIN%20__%20NIKE%20ARDILA%20__%20MABAK%20VERSI%20__%20FULL%20HD%201080p(720P_HD).mp4",
        "title": "si kabayan dana anak jin",
        "img": "https://i.pinimg.com/736x/02/79/3b/02793bb1d6106fe6e32c85bbd1a60fb9.jpg"
    },
    {
        "id": "fid20",
        "url": "https://mutia1503.ukielaki88.workers.dev/0:/Film%20jadul%20lagi/SI%20KABAYAN%20MENCARI%20JODOH%20__%20DESI%20RATNASARI%20__%20HD%20720p(720P_HD).mp4",
        "title": "si kabayan mencari jodoh",
        "img": "https://i.pinimg.com/736x/40/0a/08/400a08257f800a047c4c2e4b55b4d237.jpg"
    },
    {
        "id": "fid21",
        "url": "https://mutia1503.ukielaki88.workers.dev/0:/Film%20jadul%20lagi/SI%20KABAYAN%20SABA%20KOTA%20__%20PARAMITA%20RUSADY%20__%20FULL%20HD%201080p(720P_HD).mp4",
        "title": "si kabayan saba kota",
        "img": "https://i.pinimg.com/736x/74/85/bf/7485bf222c52c9b41ddfb9be4d2c005c.jpg"
    },
    {
        "id": "fid22",
        "url": "https://mutia1503.ukielaki88.workers.dev/0:/Film%20jadul%20lagi/SI%20RANO%20(1973)%20FULL%20MOVIE%20HD(720P_HD).mp4",
        "title": "Rano karno si rano 1973",
        "img": "https://i.pinimg.com/736x/db/0a/90/db0a90a24999a01c2e98f0f3264ef5f9.jpg"
    },
    {
        "id": "fid23",
        "url": "https://mutia1503.ukielaki88.workers.dev/0:/Film%20jadul%20lagi/TABAH%20SAMPAI%20AKHIR%20(1973)%20FULL%20MOVIE%20HD(720P_HD).mp4",
        "title": "Rano karno tabah sampai akhir 1973",
        "img": "https://i.pinimg.com/736x/f3/00/d4/f300d46564e9dd29391d55a36cb9ff17.jpg"
    },
    {
        "id": "fid24",
        "url": "https://mutia1503.ukielaki88.workers.dev/0:/Film%20jadul%20lagi/TAHU%20BERES%20(1993)%20FULL%20MOVIE%20HD(720P_60FPS).mp4",
        "title": "Kadir doyok tahu beres 1993",
        "img": "https://i.pinimg.com/736x/a1/bc/00/a1bc0030fbd6f0ebdbe9ea19c36cffad.jpg"
    },
    {
        "id": "fid25",
        "url": "https://mutia1503.ukielaki88.workers.dev/0:/Film%20jadul%20lagi/TEMPATMU%20DI%20SISIKU%20(1980)%20FULL%20MOVIE%20HD(720P_HD).mp4",
        "title": "Rano karno tempatmu di sisiku 1980",
        "img": "https://i.pinimg.com/736x/a4/1e/4a/a41e4a3d34cb0a72da53fce3a95c0ffd.jpg"
    },
    {
        "id": "fid26",
        "url": "https://mutia1503.ukielaki88.workers.dev/0:/Film%20jadul%20lagi/TITISAN%20SI%20PITUNG%20(1989)%20FULL%20MOVIE%20HD(720P_HD).mp4",
        "title": "titisan si pitung 1989",
        "img": "https://i.pinimg.com/736x/a7/17/ce/a717ce2a393528856c01f27d69ed30e0.jpg"
    },
    {
        "id": "fid27",
        "url": "https://mutia1503.ukielaki88.workers.dev/0:/Film%20jadul%20lagi/WALET%20MERAH%20(1993)%20FULL%20MOVIE%20HD%20-%20BARRY%20PRIMA_%20DEVI%20PERMATASARI_%20YOSEPH%20HUNGAN(720P_HD).mp4",
        "title": "Barry prima walet merah 1993",
        "img": "https://i.pinimg.com/736x/45/c0/e8/45c0e8e1f886e6a2c4161cd722480a96.jpg"
    },
    {
        "id": "fid28",
        "url": "https://mutia1503.ukielaki88.workers.dev/0:/Film%20jadul%20lagi/WAROK%20SINGO%20KOBRA%20(1982)%20FULL%20MOVIE%20HD(720P_60FPS).mp4",
        "title": "warok singo kobra 1982",
        "img": "https://i.pinimg.com/736x/22/b7/c8/22b7c8ce55d4ee969588dabfec6528d8.jpg"
    },
    {
        "id": "fid29",
        "url": "https://mutia1503.ukielaki88.workers.dev/0:/Film%20jadul%20lagi/ADIKKU%20KEKASIHKU%20(1989)%20FULL%20MOVIE%20HD(720P_HD).mp4",
        "title": "Rano karno adikku kekasihku",
        "img": "https://i.pinimg.com/736x/94/da/0c/94da0c8c5c48c11ea1aa3c7e300e69a7.jpg"
    },
    {
        "id": "fid30",
        "url": "https://mutia1503.ukielaki88.workers.dev/0:/Film%20jadul%20lagi/BERGOLA%20IJO%20(1983)%20FULL%20MOVIE%20HD(720P_HD).mp4",
        "title": "Barry prima bergola ijo 1983",
        "img": "https://i.pinimg.com/736x/a2/a8/65/a2a8656cb4477cae8a9c107dd4ae0dd0.jpg"
    },
    {
        "id": "fid31",
        "url": "https://mutia1503.ukielaki88.workers.dev/0:/Film%20jadul%20lagi/BUNGA%20CINTA%20KASIH%20(1981)%20FULL%20MOVIE%20HD(720P_HD).mp4",
        "title": "Rano karno bunga cinta kasih 1981",
        "img": "https://i.pinimg.com/736x/63/a7/5d/63a75d69ed7528010fc215b5a7a40282.jpg"
    },
    {
        "id": "fid32",
        "url": "https://mutia1503.ukielaki88.workers.dev/0:/Film%20jadul%20lagi/DETIK-DETIK%20CINTA%20MENYENTUH%20(1981)%20FULL%20MOVIE%20HD%20-%20TANTY%20YOSEPHA_%20ROBBY%20SUGARA_%20RANO%20KARNO(720P_HD).mp4",
        "title": "Rano karno detik cinta menyentuh 1981",
        "img": "https://i.pinimg.com/736x/01/f8/87/01f8874ece6b016a218e02a651546dab.jpg"
    },
    {
        "id": "fid33",
        "url": "https://mutia1503.ukielaki88.workers.dev/0:/Film%20jadul%20lagi/GITA%20CINTA%20DARI%20SMA%20(1979)%20FULL%20MOVIE%20HD%20-%20RANO%20KARNO_%20YESSI%20GUSMAN_%20SHIRLEY%20MALINTON_%20JUNAEDY%20SALAT(720P_HD).mp4",
        "title": "Rano karno gita cinta dari sma 1979",
        "img": "https://i.pinimg.com/736x/05/52/5a/05525aceab0e4c45ee99c7a55730a6d7.jpg"
    },
    {
        "id": "fid34",
        "url": "https://mutia1503.ukielaki88.workers.dev/0:/Film%20jadul%20lagi/MERANGKUL%20LANGIT%20(1986)%20FULL%20MOVIE%20HD(720P_HD).mp4",
        "title": "Rano karno merangkul langit 1986",
        "img": "https://i.pinimg.com/736x/b7/06/b3/b706b3a6b80145936625031624b572c4.jpg"
    },
    {
        "id": "fid35",
        "url": "https://mutia1503.ukielaki88.workers.dev/0:/Film%20jadul%20lagi/MEMBAKAR%20MATAHARI%20(1981)%20FULL%20MOVIE%20HD(720P_HD).mp4",
        "title": "Barry prima membakar matahari 1981",
        "img": "https://i.pinimg.com/736x/d4/b3/83/d4b3833bd0e7347ac1c3cca645fc605d.jpg"
    },
    {
        "id": "fid36",
        "url": "https://mutia1503.ukielaki88.workers.dev/0:/Film%20jadul%20lagi/KEN%20AROK%20_%20KEN%20DEDES%20(1983)%20FULL%20MOVIE%20HD%20-%20ADVENT%20BANGUN_%20GEORGE%20RUDY_%20EVA%20ARNAZ(720P_HD).mp4",
        "title": "ken arok ken dedes 1983",
        "img": "https://i.pinimg.com/736x/9b/91/2a/9b912a5ec3166f73cdf5f85034a7b91e.jpg"
    },
    {
        "id": "fid37",
        "url": "https://mutia1503.ukielaki88.workers.dev/0:/Film%20jadul%20lagi/KESAN%20PERTAMA%20(1985)%20FULL%20MOVIE%20HD(720P_HD).mp4",
        "title": "Barry prima kesan pertama 1985",
        "img": "https://i.pinimg.com/736x/19/f4/ac/19f4ac8c22ec296f6c4e60c77a063282.jpg"
    },
    {
        "id": "fid38",
        "url": "https://mutia1503.ukielaki88.workers.dev/0:/Album%20film%202/Indonesia%20jadul/%20Warkop.DKI.Atas.Boleh.Bawah.Boleh.1986.1080p.NF.WEB-DL.DDP2.0.H.264-UKIELAKI.mp4",
        "title": "warkop dki Atas boleh bawah boleh",
        "img": "https://i.pinimg.com/736x/f1/e1/5d/f1e15dec8d174c5388d13f512ab61905.jpg"
    },
    {
        "id": "fid39",
        "url": "https://mutia1503.ukielaki88.workers.dev/0:/Album%20film%202/Indonesia%20jadul/AKU%20BENCI%20KAMU%201987%20FULL%20MOVIE%20HD%20-%20PARAMITHA%20RUSADY,%20ADI%20BING%20SLAMET,%20NIA%20ZULKARNAEN.mp4",
        "title": "aku benci kamu",
        "img": "https://i.pinimg.com/736x/53/99/7f/53997f80f361bff4506d44a511972229.jpg"
    },
    {
        "id": "fid40",
        "url": "https://mutia1503.ukielaki88.workers.dev/0:/Album%20film%202/Indonesia%20jadul/Bajing.Ireng.Dan.Jaka.Sembung.1985.NF.WEB-DL.720p.mp4",
        "title": "Barry prima bajing ireng dan jaka sembung",
        "img": "https://i.pinimg.com/736x/43/e3/57/43e3570cd5f1a9537410852c4443af55.jpg"
    },
    {
        "id": "fid41",
        "url": "https://mutia1503.ukielaki88.workers.dev/0:/Album%20film%202/Indonesia%20jadul/BARANG%20ANTIK%201983%20FULL%20MOVIE%20HD%20-%20TETTY%20LIZ%20INDRIATI,%20CAHYONO,%20JOJON,%20UUK.mp4",
        "title": "Jojon barang antik",
        "img": "https://i.pinimg.com/736x/d6/49/01/d649017ead5fbc6b9c7d8a4086b56223.jpg"
    },
    {
        "id": "fid42",
        "url": "https://mutia1503.ukielaki88.workers.dev/0:/Album%20film%202/Indonesia%20jadul/Benyamin%20koboi%20insyaf(ukielaki).mp4",
        "title": "benyamin koboi insyaf",
        "img": "https://i.pinimg.com/736x/e8/fb/c1/e8fbc11f6c2188d23229e4dddbc54046.jpg"
    },
    {
        "id": "fid43",
        "url": "https://mutia1503.ukielaki88.workers.dev/0:/Album%20film%202/Indonesia%20jadul/BUJANG%20JELIHIN%201991%20FULL%20MOVIE%20HD%20-%20CHAIRIL%20J.M.,%20YENNY%20FARIDA,%20HENDRA%20CIPTA.mp4",
        "title": "bujang jelihin 1991",
        "img": "https://i.pinimg.com/736x/55/80/23/558023ac5246e5f1c2956c561559222c.jpg"
    },
    {
        "id": "fid44",
        "url": "https://mutia1503.ukielaki88.workers.dev/0:/Film%20jadul%20lagi/KAU%20TERCIPTA%20UNTUKKU%20(1980)%20FULL%20MOVIE%20HD(720P_HD).mp4",
        "title": "Rano karno kau tercipta untukku 1980",
        "img": "https://i.pinimg.com/736x/b0/9e/2f/b09e2f7dd8ab0f172e6921e35c566b3a.jpg"
    },
    {
        "id": "fid45",
        "url": "https://mutia1503.ukielaki88.workers.dev/0:/Album%20film%202/Indonesia%20jadul/FILM%20PENGKHIANATAN%20G30SPKI%20HD%20Version.mp4",
        "title": "pengkhianatan g30s pki",
        "img": "https://i.pinimg.com/736x/73/b4/54/73b45400d07e0f863ec9df54b0a53324.jpg"
    },
    {
        "id": "fid46",
        "url": "https://mutia1503.ukielaki88.workers.dev/0:/Album%20film%202/Indonesia%20jadul/Jaka%20sembung%20dan%20dewi%20samudra.mp4",
        "title": "Barry prima jaka sembung dan dewi samudra",
        "img": "https://i.pinimg.com/736x/a6/54/3a/a6543a6affab97106711b31b540a6b46.jpg"
    },
    {
        "id": "fid47",
        "url": "https://storage.googleapis.com/fca4362c817caf9107.appspot.com/3271af93f1d5d810dac46bf55459121a_1622960562.mp4?sumber=awal_storage",
        "title": "ateng minta kawin",
        "img": "https://i.pinimg.com/736x/d5/ba/38/d5ba387284bed45ecf38fab4c4ffd626.jpg"
    },
    {
        "id": "fid48",
        "url": "https://mutia1503.ukielaki88.workers.dev/0:/Album%20film%202/Indonesia%20jadul/KAPAN%20DIDALAM%20KAPAN%20DILUAR%201994%20FULL%20MOVIE%20HD%20-%20KADIR,%20DOYOK,%20CUT%20KEKE,%20DORCE%20GAMALAMA.mp4",
        "title": "Kadir doyok kapan di luar kapan di dalam doyok kadir",
        "img": "https://i.pinimg.com/736x/8e/26/80/8e2680640cd99c41f13189fe12ede838.jpg"
    },
    {
        "id": "fid49",
        "url": "https://mutia1503.ukielaki88.workers.dev/0:/Indonesia%20jadul/BILA%20HATI%20PEREMPUAN%20MENJERIT%20(1982)%20FULL%20MOVIE%20HD.webm",
        "title": "bila hati perempuan menjerit",
        "img": "https://i.pinimg.com/736x/ef/3f/8c/ef3f8c0a40cdbc3dcad29504c710ea31.jpg"
    },
    {
        "id": "fid50",
        "url": "https://mutia1503.ukielaki88.workers.dev/0:/Indonesia%20jadul/BISIKAN%20SETAN%20(1985)%20FULL%20MOVIE%20HD.webm",
        "title": "bisikan setan 1985",
        "img": "https://i.pinimg.com/736x/de/d7/12/ded712a5f1344cb275e510aff33c3fb9.jpg"
    },
    {
        "id": "fid51",
        "url": "https://mutia1503.ukielaki88.workers.dev/0:/Indonesia%20jadul/CEWEK%20JAGOAN%20BERAKSI%20KEMBALI%20(1981)%20FULL%20MOVIE%20HD.webm",
        "title": "Barry prima cewek jagoan beraksi kembali 1981",
        "img": "https://i.pinimg.com/736x/8c/15/be/8c15be89102020f0b8ed40ba0e611918.jpg"
    },
    {
        "id": "fid52",
        "url": "https://mutia1503.ukielaki88.workers.dev/0:/Indonesia%20jadul/DORCE%20SOK%20AKRAB%20(1989)%20FULL%20MOVIE%20HD.webm",
        "title": "Kadir doyok dorce sok akrab",
        "img": "https://i.pinimg.com/736x/4e/64/f1/4e64f15a8eee87cac1d3fc0a2710e3dc.jpg"
    },
    {
        "id": "fid53",
        "url": "https://mutia1503.ukielaki88.workers.dev/0:/Indonesia%20jadul/JANUR%20KUNING%20(1979)%20FULL%20MOVIE.webm",
        "title": "janur kuning 1979",
        "img": "https://i.pinimg.com/736x/1c/c0/4f/1cc04f2a50cac7553f432315d3d4f076.jpg"
    },
    {
        "id": "fid54",
        "url": "https://mutia1503.ukielaki88.workers.dev/0:/Indonesia%20jadul/KARMILA%20(1974)%20FULL%20MOVIE%20HD.webm",
        "title": "karmila 1974",
        "img": "https://i.pinimg.com/736x/b9/8e/8b/b98e8beb5905b606734aac57adb1458a.jpg"
    },
    {
        "id": "fid55",
        "url": "https://mutia1503.ukielaki88.workers.dev/0:/Indonesia%20jadul/MAMA%20(1972)%20FULL%20MOVIE%20HD.webm",
        "title": "mama 1972",
        "img": "https://i.pinimg.com/736x/56/e0/52/56e05271098ddb7453f1784ba75daf1b.jpg"
    },
    {
        "id": "fid56",
        "url": "https://mutia1503.ukielaki88.workers.dev/0:/Indonesia%20jadul/MARINA%20(1977)%20FULL%20MOVIE.webm",
        "title": "marina 1977",
        "img": "https://i.pinimg.com/736x/24/89/3a/24893a3750968af1ba27aada15bcd541.jpg"
    },
    {
        "id": "fid57",
        "url": "https://mutia1503.ukielaki88.workers.dev/0:/Indonesia%20jadul/MEMBURU%20MAKELAR%20MAYAT%20(1986)%20FULL%20MOVIE%20HD.webm",
        "title": "memburu makelar mayat 1986",
        "img": "https://i.pinimg.com/736x/4a/f2/94/4af294c8e6fb926ee2e44dfdc335fa32.jpg"
    },
    {
        "id": "fid58",
        "url": "https://mutia1503.ukielaki88.workers.dev/0:/Indonesia%20jadul/PEMBALASAN%20RAMBU%20(1985)%20FULL%20MOVIE%20HD.webm",
        "title": "pembalasan rambu 1985",
        "img": "https://i.pinimg.com/736x/76/fb/dc/76fbdcda2d0127f3e98f9f852a506119.jpg"
    },
    {
        "id": "fid59",
        "url": "https://mutia1503.ukielaki88.workers.dev/0:/Indonesia%20jadul/PENCURI%20CINTA%20(1984)%20FULL%20MOVIE%20HD.webm",
        "title": "pencuri cinta 1984",
        "img": "https://i.pinimg.com/736x/a8/11/95/a81195e0d887616300144d60712a0e50.jpg"
    },
    {
        "id": "fid60",
        "url": "https://mutia1503.ukielaki88.workers.dev/0:/Indonesia%20jadul/PENGANTIN%20BARU%20(1986)%20FULL%20MOVIE%20HD.webm",
        "title": "pengantin baru 1986",
        "img": "https://i.pinimg.com/736x/14/e8/23/14e82317a54528fc8e2623ffd50182e6.jpg"
    },
    {
        "id": "fid61",
        "url": "https://mutia1503.ukielaki88.workers.dev/0:/Indonesia%20jadul/PEREMPUAN%20BERGAIRAH%20(1982)%20FULL%20MOVIE.webm",
        "title": "Barry prima perempuan bergairah 1982",
        "img": "https://i.pinimg.com/736x/f0/fe/2a/f0fe2a67ead668fc2c27a9de77ad9664.jpg"
    },
    {
        "id": "fid62",
        "url": "https://mutia1503.ukielaki88.workers.dev/0:/Indonesia%20jadul/PERHITUNGAN%20TERAKHIR%20(1982)%20FULL%20MOVIE%20HD.webm",
        "title": "Barry prima perhitungan terakhir 1982",
        "img": "https://i.pinimg.com/736x/e2/52/6f/e2526fbdc9385f15c01fe2eca6c5a478.jpg"
    },
    {
        "id": "fid63",
        "url": "https://mutia1503.ukielaki88.workers.dev/0:/Indonesia%20jadul/SERBUAN%20HALILINTAR%20(1982)%20FULL%20MOVIE%20HD.webm",
        "title": "Barry prima serbuan halilintar 1982",
        "img": "https://i.pinimg.com/736x/e5/92/4b/e5924b63533f303ff72a6fb2e589f190.jpg"
    },
    {
        "id": "fid64",
        "url": "https://mutia1503.ukielaki88.workers.dev/0:/Indonesia%20jadul/SI%20GENIT%20POPPY%20(1978)%20FULL%20MOVIE%20HD.webm",
        "title": "si genit poppy 1978",
        "img": "https://i.pinimg.com/736x/45/91/c5/4591c5a9ba17506c8ac60e00072dda89.jpg"
    },
    {
        "id": "fid65",
        "url": "https://mutia1503.ukielaki88.workers.dev/0:/Album%20film%202/Indonesia%20jadul/MISTIK%20PUNAHNYA%20RAHASIA%20ILMU%20IBLIS%20LEAK%201981%20FULL%20MOVIE%20HD%20-%20ILONA%20AGATHE%20BASTIAN,%20YOS%20SANTO.mp4",
        "title": "mistik punahnya rahasia ilmu iblis leak 1981",
        "img": "https://i.pinimg.com/736x/51/1e/7d/511e7d2efcee52bd889a789f89c7374e.jpg"
    },
    {
        "id": "fid66",
        "url": "https://mutia1503.ukielaki88.workers.dev/0:/Album%20film%202/Indonesia%20jadul/Malam%20Satu%20Suro%20(1988).mp4",
        "title": "Suzzana malam satu suro 1988",
        "img": "https://i.pinimg.com/736x/2d/1c/ec/2d1cec7d43fd82a49f94bec39f937d10.jpg"
    },
    {
        "id": "fid67",
        "url": "https://mutia1503.ukielaki88.workers.dev/0:/Indonesia%20jadul/benyamin%20spion%20025.mp4",
        "title": "benyamin spion 025 1974",
        "img": "https://i.pinimg.com/736x/09/f7/80/09f7806bc07a96e1b85c5219514210fe.jpg"
    },
    {
        "id": "fid68",
        "url": "https://mutia1503.ukielaki88.workers.dev/0:/Indonesia%20jadul/elang%20putih.mp4",
        "title": "Elang laut 1984",
        "img": "https://i.pinimg.com/736x/31/66/d2/3166d2f68224c941bf71d17ae4a93fdc.jpg"
    },
    {
        "id": "fid69",
        "url": "https://mutia1503.ukielaki88.workers.dev/0:/Indonesia%20jadul/gawang%20gawat.mp4",
        "title": "gawang gawat 1984",
        "img": "https://i.pinimg.com/736x/d7/99/1b/d7991bff4e790acdf62c3c0407a85a8c.jpg"
    },
    {
        "id": "fid70",
        "url": "https://mutia1503.ukielaki88.workers.dev/0:/Indonesia%20jadul/jaka%20tingkir.mp4",
        "title": "jaka tingkir 1983",
        "img": "https://i.pinimg.com/736x/da/42/eb/da42eb76a7ba041a3dc3d7dbcb4d74c0.jpg"
    },
    {
        "id": "fid71",
        "url": "https://mutia1503.ukielaki88.workers.dev/0:/Indonesia%20jadul/kidung%20cinta.mp4",
        "title": "Rano karno kidung cinta 1985",
        "img": "https://i.pinimg.com/736x/eb/3f/d1/eb3fd1b224e03f231c9e013b40a61784.jpg"
    },
    {
        "id": "fid72",
        "url": "https://mutia1503.ukielaki88.workers.dev/0:/Indonesia%20jadul/pertarungan%20iblis%20merah.mp4",
        "title": "Barry prima pertarungan iblis merah 1988",
        "img": "https://i.pinimg.com/736x/a1/f5/dd/a1f5dded01b8168820ed8c14ad501650.jpg"
    },
    {
        "id": "fid73",
        "url": "https://mutia1503.ukielaki88.workers.dev/0:/Indonesia%20jadul/sama%20gilanya.mp4",
        "title": "Benyamin sama gila nya 1983",
        "img": "https://i.pinimg.com/736x/b1/7b/be/b17bbe3285f8070b5d008c9e43e400e5.jpg"
    },
    {
        "id": "fid74",
        "url": "https://mutia1503.ukielaki88.workers.dev/0:/Indonesia%20jadul/sesepuh%20majapahit.mp4",
        "title": "sesepuh majapahit 1995",
        "img": "https://i.pinimg.com/736x/9b/f5/69/9bf569e1f48736f3f2569b5a5dc35d33.jpg"
    },
    {
        "id": "fid75",
        "url": "https://mutia1503.ukielaki88.workers.dev/0:/Indonesia%20jadul/siluman%20buaya%20putih.mp4",
        "title": "Siluman Buaya putih 1987",
        "img": "https://i.pinimg.com/736x/95/f6/13/95f613baf86b06d2a495d03386956e17.jpg"
    },
    {
        "id": "fid76",
        "url": "https://mutia1503.ukielaki88.workers.dev/0:/Indonesia%20jadul/srigala.mp4",
        "title": "srigala 1981",
        "img": "https://i.pinimg.com/736x/8a/48/63/8a486304345c7b8ad5739aac1d17cb89.jpg"
    },
    {
        "id": "fid77",
        "url": "https://mutia1503.ukielaki88.workers.dev/0:/Album%20film%202/Indonesia%20jadul/SI%20JALU%20DUA%20PENDEKAR%20PUTIH%201990%20FULL%20MOVIE%20HD%20-%20SONNY%20DEWANTARA,%20YURIKE%20PRASTICA,%20LINA%20BUDIARTI.mp4",
        "title": "si jalu pendekar dua pendekar putih 1990",
        "img": "https://i.pinimg.com/736x/76/7f/9b/767f9b200a704a3616dfd7d0200b2fee.jpg"
    },
    {
        "id": "fid78",
        "url": "https://mutia1503.ukielaki88.workers.dev/0:/Album%20film%202/Indonesia%20jadul/Sundel%20bolong%20(1982).mp4",
        "title": "Suzzana sundel bolong 1982",
        "img": "https://i.pinimg.com/736x/14/ba/b4/14bab4ed12bf6d2033f7e489feadb150.jpg"
    },
    {
        "id": "fid79",
        "url": "https://mutia1503.ukielaki88.workers.dev/0:/Album%20film%202/Indonesia%20jadul/WARKOP%20DKI%20%20%20PINTAR%20PINTAR%20B0D0H%201980%20FULL%20MOVIE%20HD.mp4",
        "title": "warkop dki pintar-pintar bodoh",
        "img": "https://i.pinimg.com/736x/59/05/aa/5905aa6ad137bdc74b10e36787985795.jpg"
    },
    {
        "id": "fid80",
        "url": "https://mutia1503.ukielaki88.workers.dev/0:/Album%20film%202/Indonesia%20jadul/WARKOP%20DKI%20-%20DONGKRAK%20ANTIK%201982%20FULL%20MOVIE%20HD.mp4",
        "title": "warkop dki dongkrak antik",
        "img": "https://i.pinimg.com/736x/5a/36/d2/5a36d2c640b1184b9de4ba42a62c31ae.jpg"
    },
    {
        "id": "fid81",
        "url": "https://mutia1503.ukielaki88.workers.dev/0:/Album%20film%202/Indonesia%20jadul/WARKOP%20DKI%20-%20GANTIAN%20DONG%201985%20FULL%20%20MOVIE%20HD.mp4",
        "title": "warkop dki gantian dong",
        "img": "https://i.pinimg.com/736x/bf/a9/7c/bfa97ce5b1fdb6f9e32cab9bb7f89a72.jpg"
    },
    {
        "id": "fid82",
        "url": "https://mutia1503.ukielaki88.workers.dev/0:/Album%20film%202/Indonesia%20jadul/WARKOP%20DKI%20-%20ITU%20BISA%20DIATUR%201984%20FULL%20MOVIE%20HD-ukielaki.mp4",
        "title": "warkop dki itu bisa di atur",
        "img": "https://i.pinimg.com/736x/48/8a/ea/488aea93e0d205d8f4608396eda5f813.jpg"
    },
    {
        "id": "fid83",
        "url": "https://mutia1503.ukielaki88.workers.dev/0:/Album%20film%202/Indonesia%20jadul/WARKOP%20DKI%20-%20KESEMPATAN%20DALAM%20KESEMPITAN%201985%20FULL%20MOVIE%20HD.mp4",
        "title": "warkop dki kesempatan dalam kesempitan",
        "img": "https://i.pinimg.com/736x/39/fa/d2/39fad2d76e9b1b141a2567bd99341073.jpg"
    },
    {
        "id": "fid84",
        "url": "https://mutia1503.ukielaki88.workers.dev/0:/Album%20film%202/Indonesia%20jadul/Warkop.DKI.Bebas.Aturan.Main.1993.1080p.NF.WEB-DL.DDP2.0.H.264-ukielaki.mp4",
        "title": "warkop dki bebas aturan main",
        "img": "https://i.pinimg.com/736x/52/4c/8f/524c8f9e6f436a7c0dab508230b6697e.jpg"
    },
    {
        "id": "fid85",
        "url": "https://mutia1503.ukielaki88.workers.dev/0:/Album%20film%202/Indonesia%20jadul/Warkop.DKI.Depan.Bisa.Belakang.Bisa.1987.1080p.NF.WEB-DL.DDP2.0.H.264-ukielaki.mp4",
        "title": "warkop dki depan bisa belakang bisa",
        "img": "https://i.pinimg.com/736x/f9/94/d9/f994d9e22a1ef12c2ebf383714ddbc80.jpg"
    },
    {
        "id": "fid86",
        "url": "https://mutia1503.ukielaki88.workers.dev/0:/Album%20film%202/Indonesia%20jadul/Warkop.DKI.Bisa.Naik.Bisa.Turun.1991.1080p.NF.WEB-DL.DDP2.0.H.264-ukielaki.mp4",
        "title": "warkop dki bisa naik bisa turun",
        "img": "https://i.pinimg.com/736x/9d/bc/c3/9dbcc35758e3518b21a644bdcde8fc71.jpg"
    },
    {
        "id": "fid87",
        "url": "https://storage.googleapis.com/b90c80434edf473051.appspot.com/86f08d65f5139cff2d9eecd680a962de_1666237832.mp4?sumber=awal_storage",
        "title": "Warkop dki manusia enam juta dollar",
        "img": "https://i.pinimg.com/736x/bf/7d/c4/bf7dc410ae7464b2f2bc11d5f6ad4d18.jpg"
    },
    {
        "id": "fid88",
        "url": "https://ia801506.us.archive.org/9/items/ateng-kaya-mendadak-1975-hd/%20Ateng%20Kejamnya%20Ibu%20Tiri%20tak%20Sekejam%20Ibu%20Kota.mp4",
        "title": "ateng kejamnya ibu tiri tak sekejam ibu kota",
        "img": "https://i.pinimg.com/736x/b9/e2/0d/b9e20dbfbb5908d23ae96b095f2a2aa4.jpg"
    },
    {
        "id": "fid89",
        "url": "https://download.fileku.eu.org/0:/INDONESIAN/%23Film%20Indo-Malay/%23Film%20Indonesia/Ateng%20Pendekar%20Aneh/Ateng.Pendekar.Aneh.1977.720p.MOLA.WEB-DL.mkv",
        "title": "ateng pendekar aneh 1977",
        "img": "https://i.pinimg.com/736x/54/79/49/54794918ab933b5634e6e320e6a98152.jpg"
    },
    {
        "id": "fid90",
        "url": "https://ia801506.us.archive.org/9/items/ateng-kaya-mendadak-1975-hd/ATENG%20RAJA%20PENYAMUN%20%281974%29%20.mp4",
        "title": "ateng raja penyamun",
        "img": "https://i.pinimg.com/736x/04/75/75/0475759d37af169c94876694bffed9bb.jpg"
    },
    {
        "id": "fid91",
        "url": "https://ia801506.us.archive.org/9/items/ateng-kaya-mendadak-1975-hd/Si%20Pitung%20Banteng%20Betawi%20-%20Si%20Pitung%201.ia.mp4",
        "title": "si pitung banteng betawi",
        "img": "https://i.pinimg.com/736x/92/94/2e/92942edce1fc7be7142f68672f387b26.jpg"
    },
    {
        "id": "fid92",
        "url": "https://ia801506.us.archive.org/9/items/ateng-kaya-mendadak-1975-hd/Banteng%20Betawi%202%20-%20Si%20Pitung%20-%202.mp4",
        "title": "si pitung",
        "img": "https://i.pinimg.com/736x/3d/9a/5f/3d9a5f0ee8cd7907b5862416708b26da.jpg"
    },
    {
        "id": "fid93",
        "url": "https://ia801506.us.archive.org/9/items/ateng-kaya-mendadak-1975-hd/Ateng%20Dang%20Ding%20Dong.mp4",
        "title": "ateng dang ding dong",
        "img": "https://i.pinimg.com/736x/fc/a7/31/fca7310a066aa44923eb14c50f8c177d.jpg"
    },
    {
        "id": "fid94",
        "url": "https://ia801506.us.archive.org/9/items/ateng-kaya-mendadak-1975-hd/film%20indonesia%20jadul%20-%20ketemu%20jodoh%20%281973%29.mp4",
        "title": "Bagio Ketemu jodoh 1973",
        "img": "https://i.pinimg.com/736x/9d/7f/90/9d7f902b165c4a6da1a48ed6dcbd196b.jpg"
    },
    {
        "id": "fid95",
        "url": "https://ia601506.us.archive.org/9/items/ateng-kaya-mendadak-1975-hd/BAGITO%20Grup%26%20WARKOP%20Lebaran%2089%20Eps1.ia.mp4",
        "title": "Warkop dki bagito",
        "img": "https://i.pinimg.com/736x/f7/22/54/f722545935719f3622fef92fa923f3d2.jpg"
    },
    {
        "id": "fid96",
        "url": "https://ia801506.us.archive.org/9/items/ateng-kaya-mendadak-1975-hd/BAGITO%20Grup%26%20WARKOP%20Lebaran%2089%20Eps2.ia.mp4",
        "title": "warkop dki bagito",
        "img": "https://i.pinimg.com/736x/f7/22/54/f722545935719f3622fef92fa923f3d2.jpg"
    },
    {
        "id": "fid97",
        "url": "https://ia801506.us.archive.org/9/items/ateng-kaya-mendadak-1975-hd/Musuh%20Bebuyutan%20Part%201%20%28Benyamin%20Sueb%29.mp4",
        "title": "Benyamin musuh bebuyutan",
        "img": "https://i.pinimg.com/736x/9a/cb/26/9acb2666647bef24eab7150608015ad9.jpg"
    },
    {
        "id": "fid98",
        "url": "https://ia601506.us.archive.org/9/items/ateng-kaya-mendadak-1975-hd/Musuh%20Bebuyutan%20Part%202%20%28%20Benyamin%20sueb%29.mp4",
        "title": "Benyamin musuh bebuyutan 2",
        "img": "https://i.pinimg.com/736x/9a/cb/26/9acb2666647bef24eab7150608015ad9.jpg"
    },
    {
        "id": "fid99",
        "url": "https://ia803203.us.archive.org/34/items/film_indo_tahun_1980-1989/Legenda%20Roro%20Mendut%20%281982%29%20720p%20filmgrewal.blogspot.com.mp4",
        "title": "legenda roro mendut 1989",
        "img": "https://i.pinimg.com/736x/ec/46/de/ec46de8941980526818720425f6153f0.jpg"
    },
    {
        "id": "fid100",
        "url": "https://ia903203.us.archive.org/34/items/film_indo_tahun_1980-1989/Malaikat%20Bayangan%20%281988%29%20%28360p%29%20filmgrewal.blogspot.com.mp4",
        "title": "barry prima malaikat bayangan 1989",
        "img": "https://i.pinimg.com/736x/64/81/00/648100beba97f34fbe1f997fd1a4ad7c.jpg"
    },
    {
        "id": "fid101",
        "url": "https://ia804600.us.archive.org/2/items/y-2-mate.is-primitive-a.-k.-a-savage-terror-1980-indonesian-dub-1-rrx-9aa-3wmo-720p-1637822852457/Y2Mate.is%20-%20Primitive%20A.K.A%20Savage%20Terror%20(1980)%20Indonesian%20Dub-1Rrx9aa3wmo-720p-1637822852457.mp4",
        "title": "barry prima primitif",
        "img": "https://i.pinimg.com/736x/2e/35/de/2e35de42a5f20b41c3ec7ac864c17e92.jpg"
    },
    {
        "id": "fid102",
        "url": "https://ia904506.us.archive.org/30/items/naga-sakti-1986/Naga%20Sakti%20%281986%29.ia.mp4?cnt=0",
        "title": "pembalasan naga sakti 1986",
        "img": "https://i.pinimg.com/736x/0a/71/b6/0a71b6dacf3c4827313eee4d9e12ac48.jpg"
    },
    {
        "id": "fid103",
        "url": "https://ia904503.us.archive.org/19/items/ali-topan-anak-jalanan-1977/Ali%20Topan%20Anak%20Jalanan%20%281977%29.avi",
        "title": "Ali topan anak jalanan 1977",
        "img": "https://i.pinimg.com/736x/81/c3/73/81c373d14027d9401916a97c687e74cb.jpg"
    },
    {
        "id": "fid104",
        "url": "https://ia801506.us.archive.org/9/items/ateng-kaya-mendadak-1975-hd/Bing%20Slamet%20Koboi%20Cengeng%20%281974%29%20Upscale%20to%20HD.ia.mp4",
        "title": "koboi cengeng adi bing slamet",
        "img": "https://i.pinimg.com/736x/a0/26/51/a02651875d96819458b07ce9b2d93cc5.jpg"
    },
    {
        "id": "fid105",
        "url": "https://storage.googleapis.com/d196e82636de45b.appspot.com/d5950d11b8ed3c07be04376e03a2293b_1664110415.mp4?sumber=awal_storage",
        "title": "djago",
        "img": "https://i.pinimg.com/736x/dd/49/82/dd4982507debf8f55cb01a95b40b6a4f.jpg"
    }
]
